twat_video/__init__.py
twat_video/__version__.py
twat_video/twat_video.py
twat_video-2.7.5.dist-info/METADATA
twat_video-2.7.5.dist-info/WHEEL
twat_video-2.7.5.dist-info/licenses/LICENSE
twat_video-2.7.5.dist-info/RECORD
